sarif_om/__init__.py
sarif_om/_address.py
sarif_om/_artifact.py
sarif_om/_artifact_change.py
sarif_om/_artifact_content.py
sarif_om/_artifact_location.py
sarif_om/_attachment.py
sarif_om/_code_flow.py
sarif_om/_configuration_override.py
sarif_om/_conversion.py
sarif_om/_edge.py
sarif_om/_edge_traversal.py
sarif_om/_exception.py
sarif_om/_external_properties.py
sarif_om/_external_property_file_reference.py
sarif_om/_external_property_file_references.py
sarif_om/_fix.py
sarif_om/_graph.py
sarif_om/_graph_traversal.py
sarif_om/_invocation.py
sarif_om/_location.py
sarif_om/_location_relationship.py
sarif_om/_logical_location.py
sarif_om/_message.py
sarif_om/_multiformat_message_string.py
sarif_om/_node.py
sarif_om/_notification.py
sarif_om/_physical_location.py
sarif_om/_property_bag.py
sarif_om/_rectangle.py
sarif_om/_region.py
sarif_om/_replacement.py
sarif_om/_reporting_configuration.py
sarif_om/_reporting_descriptor.py
sarif_om/_reporting_descriptor_reference.py
sarif_om/_reporting_descriptor_relationship.py
sarif_om/_result.py
sarif_om/_result_provenance.py
sarif_om/_run.py
sarif_om/_run_automation_details.py
sarif_om/_sarif_log.py
sarif_om/_special_locations.py
sarif_om/_stack.py
sarif_om/_stack_frame.py
sarif_om/_suppression.py
sarif_om/_thread_flow.py
sarif_om/_thread_flow_location.py
sarif_om/_tool.py
sarif_om/_tool_component.py
sarif_om/_tool_component_reference.py
sarif_om/_translation_metadata.py
sarif_om/_version_control_details.py
sarif_om/_web_request.py
sarif_om/_web_response.py
sarif_om-1.0.4.dist-info/AUTHORS
sarif_om-1.0.4.dist-info/LICENSE
sarif_om-1.0.4.dist-info/METADATA
sarif_om-1.0.4.dist-info/WHEEL
sarif_om-1.0.4.dist-info/pbr.json
sarif_om-1.0.4.dist-info/top_level.txt
sarif_om-1.0.4.dist-info/RECORD
