Metadata-Version: 1.2
Name: sarif-om
Version: 1.0.4
Summary: Classes implementing the SARIF 2.1.0 object model.
Home-page: https://github.com/microsoft/sarif-python-om
Author: Microsoft Corporation
Author-email: v-lgold@microsoft.com
License: MIT
Platform: UNKNOWN
Classifier: Development Status :: 5 - Production/Stable
Classifier: Environment :: Console
Classifier: Intended Audience :: Developers
Classifier: Intended Audience :: Information Technology
Classifier: License :: OSI Approved :: MIT License
Classifier: Operating System :: OS Independent
Classifier: Programming Language :: Python
Classifier: Topic :: Software Development :: Libraries :: Python Modules
Requires-Python: >= 2.7
